algotrader/__init__.py
algotrader/backtest.py
algotrader/evaluation.py
algotrader/scraper.py
algotrader/agents/BaseAgent.py
algotrader/agents/__init__.py
algotrader/agents/cci_agent.py
algotrader/agents/dema_agent.py
algotrader/agents/ema_agent.py
algotrader/agents/momentum_agent.py
algotrader/agents/six_month_cycle_agent.py
algotrader/agents/sma_agent.py
algotrader/agents/tema_agent.py
algotrader/dask-agents/BaseDaskAgent.py
algotrader/dask-agents/__init__.py
algotrader/dask-agents/dask_sma_agent.py
algotrader-0.1.dev0.dist-info/METADATA
algotrader-0.1.dev0.dist-info/RECORD
algotrader-0.1.dev0.dist-info/WHEEL
algotrader-0.1.dev0.dist-info/top_level.txt
tests/__init__.py
tests/genetics.py
tests/optimise.py
tests/test.py
tests/test_backtest.py
tests/test_cci.py
tests/test_dema.py
tests/test_ema.py
tests/test_logging.py
tests/test_momentum.py
tests/test_six_month_cycle.py
tests/test_sma.py
tests/test_tema.py
