Metadata-Version: 2.1
Name: algotrader
Version: 0.1.dev0
Summary: Python implementations of commonly used trading algorithms
Home-page: https://github.com/vrishank97/AlgoTrading
Author: Vrishank Bhardwaj
Author-email: vrishank1997@gmail.com
License: UNKNOWN
Platform: UNKNOWN
Classifier: Programming Language :: Python :: 3
Classifier: License :: OSI Approved :: MIT License
Classifier: Operating System :: OS Independent
